JingtongBiteBiDierBan/README.md
JingtongBiteBiDierBan/__init__.py
JingtongBiteBiDierBan/__main__.py
JingtongBiteBiDierBan/file.epub
JingtongBiteBiDierBan/index.html
JingtongBiteBiDierBan/css/__init__.py
JingtongBiteBiDierBan/css/annotations.css
JingtongBiteBiDierBan/css/main.css
JingtongBiteBiDierBan/css/normalize.css
JingtongBiteBiDierBan/css/popup.css
JingtongBiteBiDierBan/font/__init__.py
JingtongBiteBiDierBan/font/fontello.eot
JingtongBiteBiDierBan/font/fontello.svg
JingtongBiteBiDierBan/font/fontello.ttf
JingtongBiteBiDierBan/font/fontello.woff
JingtongBiteBiDierBan/img/__init__.py
JingtongBiteBiDierBan/img/annotator-glyph-sprite.png
JingtongBiteBiDierBan/img/annotator-icon-sprite.png
JingtongBiteBiDierBan/img/apple-touch-icon.png
JingtongBiteBiDierBan/img/cancelfullscreen.png
JingtongBiteBiDierBan/img/close.png
JingtongBiteBiDierBan/img/fullscreen.png
JingtongBiteBiDierBan/img/loader.gif
JingtongBiteBiDierBan/img/menu-icon.png
JingtongBiteBiDierBan/img/save.png
JingtongBiteBiDierBan/img/saved.png
JingtongBiteBiDierBan/img/settings-s.png
JingtongBiteBiDierBan/img/settings.png
JingtongBiteBiDierBan/img/star.png
JingtongBiteBiDierBan/js/__init__.py
JingtongBiteBiDierBan/js/epub.js
JingtongBiteBiDierBan/js/epub.min.js
JingtongBiteBiDierBan/js/epub.min.map
JingtongBiteBiDierBan/js/hooks.min.js
JingtongBiteBiDierBan/js/hooks.min.map
JingtongBiteBiDierBan/js/reader.js
JingtongBiteBiDierBan/js/reader.js.map
JingtongBiteBiDierBan/js/reader.min.js
JingtongBiteBiDierBan/js/reader.min.map
JingtongBiteBiDierBan/js/hooks/__init__.py
JingtongBiteBiDierBan/js/hooks/extensions/__init__.py
JingtongBiteBiDierBan/js/hooks/extensions/highlight.js
JingtongBiteBiDierBan/js/libs/__init__.py
JingtongBiteBiDierBan/js/libs/jquery.min.js
JingtongBiteBiDierBan/js/libs/localforage.min.js
JingtongBiteBiDierBan/js/libs/screenfull.js
JingtongBiteBiDierBan/js/libs/screenfull.min.js
JingtongBiteBiDierBan/js/libs/zip.min.js
JingtongBiteBiDierBan/js/plugins/__init__.py
jingtong_bite_bi_dier_ban-2024.3.3.0.dist-info/METADATA
jingtong_bite_bi_dier_ban-2024.3.3.0.dist-info/WHEEL
jingtong_bite_bi_dier_ban-2024.3.3.0.dist-info/entry_points.txt
jingtong_bite_bi_dier_ban-2024.3.3.0.dist-info/top_level.txt
jingtong_bite_bi_dier_ban-2024.3.3.0.dist-info/RECORD
